Metadata-Version: 1.0
Name: hungdq97-distributions
Version: 0.1
Summary: Gaussian distributions
Home-page: UNKNOWN
Author: UNKNOWN
Author-email: hungdinhquang97@gmail.com
License: UNKNOWN
Platform: UNKNOWN
